dayspan/__init__.py
dayspan/calculator.py
dayspan/cli.py
dayspan-1.0.11.dist-info/licenses/LICENSE
dayspan-1.0.11.dist-info/METADATA
dayspan-1.0.11.dist-info/WHEEL
dayspan-1.0.11.dist-info/entry_points.txt
dayspan-1.0.11.dist-info/top_level.txt
dayspan-1.0.11.dist-info/RECORD
